.DS_Store
build_deps/__init__.py
build_deps/build_deps.py
build_deps-0.0.1.dist-info/LICENSE
build_deps-0.0.1.dist-info/METADATA
build_deps-0.0.1.dist-info/WHEEL
build_deps-0.0.1.dist-info/entry_points.txt
build_deps-0.0.1.dist-info/top_level.txt
build_deps-0.0.1.dist-info/RECORD
