Metadata-Version: 2.1
Name: build-deps
Version: 0.0.1
Summary: A python script to automate building of native dependencies
Home-page: https://github.com/khrykin/build_deps
Author: Dmitry Khrykib
Author-email: khrykin@me.com
License: UNKNOWN
Platform: UNKNOWN
Classifier: Programming Language :: Python :: 3
Classifier: License :: OSI Approved :: MIT License
Classifier: Operating System :: OS Independent
Requires-Python: >=3.6
